[
    {
        "title": "Test Title",
        "text": "Test text"
    },
    {
        "title": "books to read",
        "text": "fdsdfd",
        "note_id": "aaa3"
    },
    {
        "title": "fdsdf",
        "text": "fdsdfg",
        "note_id": "b3a5"
    },
    {
        "title": "hi",
        "text": "fds\n",
        "note_id": "14b4"
    },
    {
        "title": "hello",
        "text": "gfdsdfghgfds",
        "note_id": "bd36"
    },
    {
        "title": "dsasdf",
        "text": "fdsasd",
        "note_id": "e567"
    }
]